term_tz/__init__.py
term_tz/color.py
term_tz/format.py
term_tz/types.py
term_tz/draw/__init__.py
term_tz/draw/font.py
term_tz/draw/image.py
term_tz/draw/utils.py
term_tz/draw/fonts/__init__.py
term_tz/draw/fonts/font_map.py
term_tz-0.1.1b0.dist-info/licenses/LICENSE
term_tz-0.1.1b0.dist-info/METADATA
term_tz-0.1.1b0.dist-info/WHEEL
term_tz-0.1.1b0.dist-info/top_level.txt
term_tz-0.1.1b0.dist-info/RECORD
