Metadata-Version: 2.4
Name: term-tz
Version: 0.1.1b0
Summary: A Python library for enhanced terminal display.
Author-email: Zhen Tian <zhen.tian.cs@gmail.com>
Project-URL: Homepage, https://github.com/tinchen777/term-tz.git
Project-URL: Repository, https://github.com/tinchen777/term-tz.git
Project-URL: Issues, https://github.com/tinchen777/term-tz.git/issues
Requires-Python: >=3.9
License-File: LICENSE
Requires-Dist: Pillow<11,>=9.0
Requires-Dist: numpy<2.0,>=1.21
Dynamic: license-file
